Metadata-Version: 1.0
Name: Adversary
Version: 1.1.1
Summary: Creates adversarial text examples for machine learning models
Home-page: https://github.com/airbnb/artificial-adversary
Author: Devin Soni
Author-email: devinsoni1010@gmail.com
License: MIT
Platform: UNKNOWN
